README.md
setup.cfg
setup.py
eis/__init__.py
eis/dunning/__init__.py
eis/dunning/api_client.py
eis/dunning/configuration.py
eis/dunning/exceptions.py
eis/dunning/model_utils.py
eis/dunning/rest.py
eis/dunning/api/__init__.py
eis/dunning/api/default_api.py
eis/dunning/api/dunning_configuration_api.py
eis/dunning/api/dunning_position_api.py
eis/dunning/apis/__init__.py
eis/dunning/model/__init__.py
eis/dunning/model/calculate_dunning_for_invoice_request_dto_rest.py
eis/dunning/model/calculate_dunning_for_invoice_response_class.py
eis/dunning/model/create_dunning_config_request_dto.py
eis/dunning/model/create_dunning_config_response_class.py
eis/dunning/model/create_dunning_for_invoice_request_dto_rest.py
eis/dunning/model/create_dunning_position_for_invoice_response_class.py
eis/dunning/model/create_dunning_position_request_dto_rest.py
eis/dunning/model/create_dunning_position_response_class.py
eis/dunning/model/dunning_config_class.py
eis/dunning/model/dunning_configuration_class.py
eis/dunning/model/dunning_configuration_request_dto.py
eis/dunning/model/dunning_level_class.py
eis/dunning/model/dunning_level_request_dto.py
eis/dunning/model/dunning_position_calculated_class.py
eis/dunning/model/dunning_position_class.py
eis/dunning/model/get_dunning_config_response_class.py
eis/dunning/model/get_dunning_position_response_class.py
eis/dunning/model/inline_response200.py
eis/dunning/model/inline_response503.py
eis/dunning/model/list_dunning_config_response_class.py
eis/dunning/model/list_dunning_position_response_class.py
eis/dunning/model/update_dunning_config_request_dto.py
eis/dunning/model/update_dunning_config_response_class.py
eis/dunning/models/__init__.py
eis_dunning.egg-info/PKG-INFO
eis_dunning.egg-info/SOURCES.txt
eis_dunning.egg-info/dependency_links.txt
eis_dunning.egg-info/requires.txt
eis_dunning.egg-info/top_level.txt
test/test_calculate_dunning_for_invoice_request_dto_rest.py
test/test_calculate_dunning_for_invoice_response_class.py
test/test_create_dunning_config_request_dto.py
test/test_create_dunning_config_response_class.py
test/test_create_dunning_for_invoice_request_dto_rest.py
