Metadata-Version: 2.1
Name: eis-dunning
Version: 1.6.0
Summary: EMIL DunningService
Home-page: UNKNOWN
Author: Contact us
Author-email: kontakt@emil.de
License: UNKNOWN
Keywords: OpenAPI,OpenAPI-Generator,EMIL DunningService
Platform: UNKNOWN
Requires-Python: >=3.6
